JSTPyGame
tests
