Metadata-Version: 1.1
Name: JSTPyGame
Version: 0.1.5
Summary: My first Python game
Home-page: https://github.com/slidest/JSTPyGame
Author: Julien SIDOT
Author-email: julien.sidot@gmail.com
License: WTFPL
Platform: UNKNOWN
Classifier: Programming Language :: Python
Classifier: Development Status :: 1 - Planning
Classifier: License :: OSI Approved
Classifier: Natural Language :: French
Classifier: Operating System :: OS Independent
Classifier: Programming Language :: Python :: 2.7
